eolearn/__init__.py
eolearn/py.typed
eolearn/core/__init__.py
eolearn/core/constants.py
eolearn/core/core_tasks.py
eolearn/core/eodata.py
eolearn/core/eodata_io.py
eolearn/core/eodata_merge.py
eolearn/core/eoexecution.py
eolearn/core/eonode.py
eolearn/core/eotask.py
eolearn/core/eoworkflow.py
eolearn/core/eoworkflow_tasks.py
eolearn/core/exceptions.py
eolearn/core/graph.py
eolearn/core/types.py
eolearn/core/extra/__init__.py
eolearn/core/extra/ray.py
eolearn/core/utils/__init__.py
eolearn/core/utils/common.py
eolearn/core/utils/fs.py
eolearn/core/utils/logging.py
eolearn/core/utils/parallelize.py
eolearn/core/utils/parsing.py
eolearn/core/utils/raster.py
eolearn/core/utils/testing.py
eolearn/core/utils/types.py
eolearn/coregistration/__init__.py
eolearn/coregistration/coregistration.py
eolearn/features/__init__.py
eolearn/features/feature_manipulation.py
eolearn/features/ndi.py
eolearn/features/utils.py
eolearn/features/extra/__init__.py
eolearn/features/extra/clustering.py
eolearn/features/extra/interpolation.py
eolearn/geometry/__init__.py
eolearn/geometry/morphology.py
eolearn/geometry/transformations.py
eolearn/io/__init__.py
eolearn/io/geometry_io.py
eolearn/io/raster_io.py
eolearn/io/sentinelhub_process.py
eolearn/mask/__init__.py
eolearn/mask/masking.py
eolearn/mask/snow_mask.py
eolearn/mask/extra/__init__.py
eolearn/mask/extra/cloud_mask.py
eolearn/ml_tools/__init__.py
eolearn/ml_tools/sampling.py
eolearn/visualization/__init__.py
eolearn/visualization/eoexecutor.py
eolearn/visualization/eopatch.py
eolearn/visualization/eoworkflow.py
eolearn/visualization/utils.py
eolearn/visualization/report_templates/report.html
eo_learn-1.5.7.dist-info/METADATA
eo_learn-1.5.7.dist-info/WHEEL
eo_learn-1.5.7.dist-info/licenses/LICENSE
eo_learn-1.5.7.dist-info/RECORD
