Metadata-Version: 2.3
Name: eo-learn
Version: 1.5.7
Summary: Earth observation processing framework for machine learning in Python
Project-URL: Homepage, https://github.com/sentinel-hub/eo-learn
Project-URL: Documentation, https://eo-learn.readthedocs.io
Project-URL: Issues, https://github.com/sentinel-hub/eo-learn/issues
Project-URL: Source, https://github.com/sentinel-hub/eo-learn
Project-URL: Forum, https://forum.sentinel-hub.com
Author-email: Sinergise EO research team <eoresearch@sinergise.com>
License: MIT License
License-File: LICENSE
Classifier: Development Status :: 5 - Production/Stable
Classifier: Intended Audience :: Developers
Classifier: Intended Audience :: Education
Classifier: Intended Audience :: Science/Research
Classifier: License :: OSI Approved :: MIT License
Classifier: Operating System :: MacOS
Classifier: Operating System :: Microsoft :: Windows
Classifier: Operating System :: Unix
Classifier: Programming Language :: Python
Classifier: Programming Language :: Python :: 3
Classifier: Programming Language :: Python :: 3.8
Classifier: Programming Language :: Python :: 3.9
Classifier: Programming Language :: Python :: 3.10
Classifier: Programming Language :: Python :: 3.11
Classifier: Topic :: Scientific/Engineering
Classifier: Topic :: Scientific/Engineering :: GIS
Classifier: Topic :: Scientific/Engineering :: Image Processing
Requires-Python: >=3.8
Requires-Dist: affine
Requires-Dist: boto3
Requires-Dist: fiona<1.10,>=1.8.18; python_version < '3.9'
Requires-Dist: fiona>=1.8.18; python_version >= '3.9'
Requires-Dist: fs
Requires-Dist: fs-s3fs
Requires-Dist: geopandas<1,>=0.11.0; python_version < '3.9'
Requires-Dist: geopandas<1,>=0.14.4; python_version >= '3.9'
Requires-Dist: numpy>=1.20.0
Requires-Dist: opencv-python-headless
Requires-Dist: python-dateutil
Requires-Dist: rasterio>=1.3.8
Requires-Dist: sentinelhub>=3.9.0
Requires-Dist: shapely
Requires-Dist: tqdm>=4.27
Requires-Dist: typing-extensions>=4.5.0
Provides-Extra: dev
Requires-Dist: build; extra == 'dev'
Requires-Dist: graphviz>=0.10.1; extra == 'dev'
Requires-Dist: hypothesis; extra == 'dev'
Requires-Dist: jinja2; extra == 'dev'
Requires-Dist: matplotlib; extra == 'dev'
Requires-Dist: moto[s3]>=5.0.0; extra == 'dev'
Requires-Dist: mypy>=0.990; extra == 'dev'
Requires-Dist: numba>=0.53.0; extra == 'dev'
Requires-Dist: pygments; extra == 'dev'
Requires-Dist: pylint>=2.14.0; extra == 'dev'
Requires-Dist: pytest-cov; extra == 'dev'
Requires-Dist: pytest-mock; extra == 'dev'
Requires-Dist: pytest>=7.0.0; extra == 'dev'
Requires-Dist: ray[default]; extra == 'dev'
Requires-Dist: s2cloudless; extra == 'dev'
Requires-Dist: s3fs; extra == 'dev'
Requires-Dist: scikit-learn; extra == 'dev'
Requires-Dist: scipy; extra == 'dev'
Requires-Dist: twine; extra == 'dev'
Requires-Dist: types-python-dateutil; extra == 'dev'
Requires-Dist: zarr; extra == 'dev'
Provides-Extra: docs
Requires-Dist: graphviz>=0.10.1; extra == 'docs'
Requires-Dist: jinja2; extra == 'docs'
Requires-Dist: jupyter; extra == 'docs'
Requires-Dist: matplotlib; extra == 'docs'
Requires-Dist: nbsphinx; extra == 'docs'
Requires-Dist: numba>=0.53.0; extra == 'docs'
Requires-Dist: pygments; extra == 'docs'
Requires-Dist: ray[default]; extra == 'docs'
Requires-Dist: s2cloudless; extra == 'docs'
Requires-Dist: s3fs; extra == 'docs'
Requires-Dist: scikit-learn; extra == 'docs'
Requires-Dist: scipy; extra == 'docs'
Requires-Dist: sphinx-mdinclude==0.5.4; extra == 'docs'
Requires-Dist: sphinx-rtd-theme==1.3.0; extra == 'docs'
Requires-Dist: sphinx==7.1.2; extra == 'docs'
Requires-Dist: zarr; extra == 'docs'
Provides-Extra: extra
Requires-Dist: numba>=0.53.0; extra == 'extra'
Requires-Dist: s2cloudless; extra == 'extra'
Requires-Dist: scikit-learn; extra == 'extra'
Requires-Dist: scipy; extra == 'extra'
Provides-Extra: full
Requires-Dist: graphviz>=0.10.1; extra == 'full'
Requires-Dist: jinja2; extra == 'full'
Requires-Dist: matplotlib; extra == 'full'
Requires-Dist: numba>=0.53.0; extra == 'full'
Requires-Dist: pygments; extra == 'full'
Requires-Dist: ray[default]; extra == 'full'
Requires-Dist: s2cloudless; extra == 'full'
Requires-Dist: s3fs; extra == 'full'
Requires-Dist: scikit-learn; extra == 'full'
Requires-Dist: scipy; extra == 'full'
Requires-Dist: zarr; extra == 'full'
Provides-Extra: ray
Requires-Dist: ray[default]; extra == 'ray'
Provides-Extra: visualization
Requires-Dist: graphviz>=0.10.1; extra == 'visualization'
Requires-Dist: jinja2; extra == 'visualization'
Requires-Dist: matplotlib; extra == 'visualization'
Requires-Dist: pygments; extra == 'visualization'
Provides-Extra: zarr
Requires-Dist: s3fs; extra == 'zarr'
Requires-Dist: zarr; extra == 'zarr'
